{
  "openapi": "3.0.1",
  "info": {
    "title": "DiceroWebAPI",
    "version": "1.0"
  },
  "paths": {
    "/api/Auth/login": {
      "post": {
        "tags": [
          "Auth"
        ],
        "requestBody": {
          "content": {
            "application/json": {
              "schema": {
                "$ref": "#/components/schemas/LoginRequestDTO"
              }
            },
            "text/json": {
              "schema": {
                "$ref": "#/components/schemas/LoginRequestDTO"
              }
            },
            "application/*+json": {
              "schema": {
                "$ref": "#/components/schemas/LoginRequestDTO"
              }
            }
          }
        },
        "responses": {
          "200": {
            "description": "OK"
          }
        }
      }
    },
    "/api/Auth/register": {
      "post": {
        "tags": [
          "Auth"
        ],
        "requestBody": {
          "content": {
            "application/json": {
              "schema": {
                "$ref": "#/components/schemas/UserCreateDTO"
              }
            },
            "text/json": {
              "schema": {
                "$ref": "#/components/schemas/UserCreateDTO"
              }
            },
            "application/*+json": {
              "schema": {
                "$ref": "#/components/schemas/UserCreateDTO"
              }
            }
          }
        },
        "responses": {
          "200": {
            "description": "OK"
          }
        }
      }
    },
    "/api/BoardGame": {
      "get": {
        "tags": [
          "BoardGame"
        ],
        "responses": {
          "200": {
            "description": "OK"
          }
        }
      },
      "post": {
        "tags": [
          "BoardGame"
        ],
        "requestBody": {
          "content": {
            "application/json": {
              "schema": {
                "$ref": "#/components/schemas/BoardGameCreateDTO"
              }
            },
            "text/json": {
              "schema": {
                "$ref": "#/components/schemas/BoardGameCreateDTO"
              }
            },
            "application/*+json": {
              "schema": {
                "$ref": "#/components/schemas/BoardGameCreateDTO"
              }
            }
          }
        },
        "responses": {
          "200": {
            "description": "OK"
          }
        }
      }
    },
    "/api/BoardGame/{id}": {
      "get": {
        "tags": [
          "BoardGame"
        ],
        "parameters": [
          {
            "name": "id",
            "in": "path",
            "required": true,
            "schema": {
              "type": "integer",
              "format": "int32"
            }
          }
        ],
        "responses": {
          "200": {
            "description": "OK"
          }
        }
      },
      "put": {
        "tags": [
          "BoardGame"
        ],
        "parameters": [
          {
            "name": "id",
            "in": "path",
            "required": true,
            "schema": {
              "type": "integer",
              "format": "int32"
            }
          }
        ],
        "requestBody": {
          "content": {
            "application/json": {
              "schema": {
                "$ref": "#/components/schemas/BoardgameUpdateDTO"
              }
            },
            "text/json": {
              "schema": {
                "$ref": "#/components/schemas/BoardgameUpdateDTO"
              }
            },
            "application/*+json": {
              "schema": {
                "$ref": "#/components/schemas/BoardgameUpdateDTO"
              }
            }
          }
        },
        "responses": {
          "200": {
            "description": "OK"
          }
        }
      },
      "delete": {
        "tags": [
          "BoardGame"
        ],
        "parameters": [
          {
            "name": "id",
            "in": "path",
            "required": true,
            "schema": {
              "type": "integer",
              "format": "int32"
            }
          }
        ],
        "responses": {
          "200": {
            "description": "OK"
          }
        }
      }
    },
    "/api/User": {
      "get": {
        "tags": [
          "User"
        ],
        "responses": {
          "200": {
            "description": "OK"
          }
        }
      }
    },
    "/api/User/{id}": {
      "get": {
        "tags": [
          "User"
        ],
        "parameters": [
          {
            "name": "id",
            "in": "path",
            "required": true,
            "schema": {
              "type": "integer",
              "format": "int32"
            }
          }
        ],
        "responses": {
          "200": {
            "description": "OK"
          }
        }
      }
    }
  },
  "components": {
    "schemas": {
      "BoardGameCreateDTO": {
        "required": [
          "gamePlay",
          "ownerId",
          "title"
        ],
        "type": "object",
        "properties": {
          "title": {
            "maxLength": 200,
            "minLength": 0,
            "type": "string"
          },
          "numberOfPlayers": {
            "maximum": 100,
            "minimum": 1,
            "type": "integer",
            "format": "int32"
          },
          "gamePlay": {
            "$ref": "#/components/schemas/GamePlay"
          },
          "description": {
            "type": "string",
            "nullable": true
          },
          "priceSell": {
            "minimum": 0,
            "type": "number",
            "format": "double",
            "nullable": true
          },
          "priceRent": {
            "minimum": 0,
            "type": "number",
            "format": "double",
            "nullable": true
          },
          "ownerId": {
            "type": "integer",
            "format": "int32"
          }
        },
        "additionalProperties": false
      },
      "BoardgameUpdateDTO": {
        "required": [
          "gamePlay",
          "title"
        ],
        "type": "object",
        "properties": {
          "title": {
            "maxLength": 100,
            "minLength": 0,
            "type": "string"
          },
          "numberOfPlayers": {
            "maximum": 2147483647,
            "minimum": 1,
            "type": "integer",
            "format": "int32"
          },
          "gamePlay": {
            "$ref": "#/components/schemas/GamePlay"
          },
          "description": {
            "maxLength": 1000,
            "minLength": 0,
            "type": "string",
            "nullable": true
          },
          "priceSell": {
            "minimum": 0,
            "type": "number",
            "format": "double",
            "nullable": true
          },
          "priceRent": {
            "minimum": 0,
            "type": "number",
            "format": "double",
            "nullable": true
          }
        },
        "additionalProperties": false
      },
      "GamePlay": {
        "enum": [
          1,
          2,
          3,
          4,
          5,
          6,
          7,
          8,
          9,
          10
        ],
        "type": "integer",
        "format": "int32"
      },
      "LoginRequestDTO": {
        "required": [
          "email",
          "password"
        ],
        "type": "object",
        "properties": {
          "email": {
            "minLength": 1,
            "type": "string",
            "format": "email"
          },
          "password": {
            "minLength": 1,
            "type": "string"
          }
        },
        "additionalProperties": false
      },
      "UserCreateDTO": {
        "required": [
          "email",
          "fullName",
          "password"
        ],
        "type": "object",
        "properties": {
          "email": {
            "minLength": 1,
            "type": "string",
            "format": "email"
          },
          "password": {
            "minLength": 6,
            "type": "string"
          },
          "fullName": {
            "maxLength": 100,
            "minLength": 0,
            "type": "string"
          }
        },
        "additionalProperties": false
      }
    },
    "securitySchemes": {
      "Bearer": {
        "type": "http",
        "description": "Nhập token dạng: Bearer {your token}",
        "scheme": "bearer",
        "bearerFormat": "JWT"
      }
    }
  },
  "security": [
    {
      "Bearer": [ ]
    }
  ]
}